magiclink/__init__.py
magiclink/apps.py
magiclink/backends.py
magiclink/forms.py
magiclink/helpers.py
magiclink/management/__init__.py
magiclink/management/commands/__init__.py
magiclink/management/commands/magiclink_clear_logins.py
magiclink/migrations/0001_initial.py
magiclink/migrations/0002_magiclinkunsubscribe.py
magiclink/migrations/__init__.py
magiclink/models.py
magiclink/settings.py
magiclink/templates/magiclink/login.html
magiclink/templates/magiclink/login_email.html
magiclink/templates/magiclink/login_email.txt
magiclink/templates/magiclink/login_failed.html
magiclink/templates/magiclink/login_sent.html
magiclink/templates/magiclink/signup.html
magiclink/urls.py
magiclink/utils.py
magiclink/views.py
django_magiclink-1.3.0.dist-info/LICENSE.md
django_magiclink-1.3.0.dist-info/METADATA
django_magiclink-1.3.0.dist-info/WHEEL
django_magiclink-1.3.0.dist-info/RECORD
