Metadata-Version: 2.1
Name: django-magiclink
Version: 1.3.0
Summary: Passwordless authentication for Django with Magic Links
Home-page: https://github.com/pyepye/django-magiclink
License: MIT
Keywords: magic link,authentication,passwordless
Author: Matt Pye
Author-email: pyematt@gmail.com
Requires-Python: >=3.6,<4.0
Classifier: License :: OSI Approved :: MIT License
Classifier: Programming Language :: Python :: 3
Classifier: Programming Language :: Python :: 3.6
Classifier: Programming Language :: Python :: 3.7
Classifier: Programming Language :: Python :: 3.8
Classifier: Programming Language :: Python :: 3.9
Classifier: Programming Language :: Python :: 3.10
Classifier: Programming Language :: Python :: 3.11
Requires-Dist: Django (>=2.1)
Requires-Dist: packaging (>=20.9,<22.0)
Project-URL: Repository, https://github.com/pyepye/django-magiclink
